{
  "version": "7",
  "dialect": "postgresql",
  "entries": [
    {
      "idx": 0,
      "version": "7",
      "when": 1764272432009,
      "tag": "0000_shiny_landau",
      "breakpoints": true
    },
    {
      "idx": 1,
      "version": "7",
      "when": 1766594910646,
      "tag": "0001_spooky_marten_broadcloak",
      "breakpoints": true
    },
    {
      "idx": 2,
      "version": "7",
      "when": 1767265052703,
      "tag": "0002_busy_microchip",
      "breakpoints": true
    },
    {
      "idx": 3,
      "version": "7",
      "when": 1767265246161,
      "tag": "0003_legal_sumo",
      "breakpoints": true
    },
    {
      "idx": 4,
      "version": "7",
      "when": 1767265306139,
      "tag": "0004_lively_randall",
      "breakpoints": true
    },
    {
      "idx": 5,
      "version": "7",
      "when": 1767273441215,
      "tag": "0005_redundant_ogun",
      "breakpoints": true
    },
    {
      "idx": 6,
      "version": "7",
      "when": 1771064042905,
      "tag": "0006_aberrant_natasha_romanoff",
      "breakpoints": true
    },
    {
      "idx": 7,
      "version": "7",
      "when": 1771426365092,
      "tag": "0007_aberrant_onslaught",
      "breakpoints": true
    },
    {
      "idx": 8,
      "version": "7",
      "when": 1771428133310,
      "tag": "0008_smooth_catseye",
      "breakpoints": true
    },
    {
      "idx": 9,
      "version": "7",
      "when": 1771460319094,
      "tag": "0009_young_piledriver",
      "breakpoints": true
    }
  ]
}